tests/__init__.py
webclipper/__init__.py
webclipper/apps.py
webclipper/rules.py
webclipper/admin/__init__.py
webclipper/admin/admin.py
webclipper/admin/helpers.py
webclipper/migrations/0001_initial.py
webclipper/migrations/__init__.py
webclipper/models/__init__.py
webclipper/models/abstracts.py
webclipper/models/mixins.py
webclipper/models/models.py
webclipper/rest/__init__.py
webclipper/rest/permissions.py
webclipper/rest/routes.py
webclipper/rest/serializers/__init__.py
webclipper/rest/serializers/base.py
webclipper/rest/serializers/serializers.py
webclipper/rest/viewsets/__init__.py
webclipper/rest/viewsets/base.py
webclipper/rest/viewsets/viewsets.py
dj_kaos_webclipper-0.1.0.dist-info/LICENSE
dj_kaos_webclipper-0.1.0.dist-info/METADATA
dj_kaos_webclipper-0.1.0.dist-info/WHEEL
dj_kaos_webclipper-0.1.0.dist-info/top_level.txt
dj_kaos_webclipper-0.1.0.dist-info/RECORD
