Metadata-Version: 2.1
Name: dj-kaos-webclipper
Version: 0.1.0
Summary: Clip web pages html and store in Django
Home-page: https://github.com/kaoslabsinc/dj-kaos-webclipper
Author: Kaos Labs Inc.
Author-email: keyvan@keyvanm.com
License: BSD-3-Clause
Keywords: django,clipper,webclipper,web clipper,scarping,scrape,kaos
Platform: UNKNOWN
Classifier: Environment :: Web Environment
Classifier: Framework :: Django
Classifier: Framework :: Django :: 3.2
Classifier: Intended Audience :: Developers
Classifier: License :: OSI Approved :: BSD License
Classifier: Operating System :: OS Independent
Classifier: Programming Language :: Python
Classifier: Programming Language :: Python :: 3
Classifier: Programming Language :: Python :: 3 :: Only
Classifier: Programming Language :: Python :: 3.7
Classifier: Programming Language :: Python :: 3.8
Classifier: Programming Language :: Python :: 3.9
Classifier: Topic :: Internet :: WWW/HTTP
Classifier: Topic :: Internet :: WWW/HTTP :: Dynamic Content
License-File: LICENSE
Requires-Dist: django (>=3.2)
Requires-Dist: django-model-utils (>=4.2.0)
Requires-Dist: django-building-blocks (>=0.1.0a6)
Requires-Dist: rules (>=3.3)
Requires-Dist: djangorestframework (>=3.13.1)
Requires-Dist: django-filter (>=21.1)
Requires-Dist: scrapy (~=2.6)
Provides-Extra: test
Requires-Dist: tox ; extra == 'test'
Requires-Dist: pytest-django ; extra == 'test'
Requires-Dist: pytest-pythonpath ; extra == 'test'
Requires-Dist: pytest-cov ; extra == 'test'
